graphql_schema_parse/__init__.py
graphql_schema_parse/cli.py
graphql_schema_parse/src.py
graphql_schema_parse-0.2.2.dist-info/entry_points.txt
graphql_schema_parse-0.2.2.dist-info/LICENSE
graphql_schema_parse-0.2.2.dist-info/WHEEL
graphql_schema_parse-0.2.2.dist-info/METADATA
graphql_schema_parse-0.2.2.dist-info/RECORD
