Metadata-Version: 2.1
Name: graphql-schema-parse
Version: 0.2.2
Summary: Graphql文档解析工具，提供解析成前端Postman可用的query语句(.gql) / RESTFul可使用的(.json)文件能力 / sqlmap可用的(.txt)扫描文件能力
Home-page: https://github.com/zy7y/graphql-schema-parse.git
License: MIT
Keywords: graphql,restful,parse,gql,test,sqlmap
Author: 柒意
Author-email: 396667207@qq.com
Requires-Python: >=3.9,<4.0
Classifier: License :: OSI Approved :: MIT License
Classifier: Programming Language :: Python :: 3
Classifier: Programming Language :: Python :: 3.10
Classifier: Programming Language :: Python :: 3.9
Requires-Dist: Jinja2 (>=3.0.3,<4.0.0)
Requires-Dist: graphql-core (>=3.2.0,<4.0.0)
Requires-Dist: typer (>=0.4.0,<0.5.0)
Project-URL: Repository, https://github.com/zy7y/graphql-schema-parse.git
